metric_py.libs/libopenblas-r0-f650aae0.3.3.so
metric_py.libs/libgfortran-4fc760a1.so.3.0.0
metric_py.libs/libquadmath-30d679e1.so.0.0.0
metric/_common.py
metric/metrics.py
metric/__init__.py
metric/mapping/koc.py
metric/mapping/__init__.py
metric/_impl/utils.cpython-36m-x86_64-linux-gnu.so
metric/_impl/mapping.cpython-36m-x86_64-linux-gnu.so
metric/_impl/entropy.cpython-36m-x86_64-linux-gnu.so
metric/_impl/esn.cpython-36m-x86_64-linux-gnu.so
metric/_impl/space.cpython-36m-x86_64-linux-gnu.so
metric/_impl/transform.cpython-36m-x86_64-linux-gnu.so
metric/_impl/koc.cpython-36m-x86_64-linux-gnu.so
metric/_impl/distance.cpython-36m-x86_64-linux-gnu.so
metric/_impl/standards.cpython-36m-x86_64-linux-gnu.so
metric/_impl/voi.cpython-36m-x86_64-linux-gnu.so
metric/_impl/redif.cpython-36m-x86_64-linux-gnu.so
metric/_impl/ensembles.cpython-36m-x86_64-linux-gnu.so
metric/_impl/metric.cpython-36m-x86_64-linux-gnu.so
metric/_impl/dt.cpython-36m-x86_64-linux-gnu.so
metric/_impl/affprop.cpython-36m-x86_64-linux-gnu.so
metric/_impl/__init__.py
metric/_impl/mgc.cpython-36m-x86_64-linux-gnu.so
metric/_impl/dbscan.cpython-36m-x86_64-linux-gnu.so
metric/space/matrix.py
metric/space/__init__.py
metric/transform/__init__.py
metric/correlation/mgc.py
metric/correlation/__init__.py
metric/correlation/entropy.py
metric/utils/misc.py
metric/utils/__init__.py
metric/distance/emd.py
metric/distance/__init__.py
metric_py-0.0.6.dist-info/top_level.txt
metric_py-0.0.6.dist-info/RECORD
metric_py-0.0.6.dist-info/METADATA
metric_py-0.0.6.dist-info/WHEEL
